ASCII_PyGraphics/__init__.py
ASCII_PyGraphics/asciigraphics.py
ASCII_PyGraphics-1.0.4.dist-info/LICENSE.txt
ASCII_PyGraphics-1.0.4.dist-info/METADATA
ASCII_PyGraphics-1.0.4.dist-info/WHEEL
ASCII_PyGraphics-1.0.4.dist-info/top_level.txt
ASCII_PyGraphics-1.0.4.dist-info/RECORD
