Metadata-Version: 2.1
Name: ASCII-PyGraphics
Version: 1.0.4
Home-page: https://github.com/PreciousFood/ASCII_PyGraphics
Author: Precious Food
Author-email: preciousfood84@gmail.com
License: MIT
License-File: LICENSE.txt
Requires-Dist: numpy
Requires-Dist: pynput
